[
  {
    "name": "Body",
    "parent": "",
    "centerX": "-0.029",
    "centerY": "2.549",
    "centerZ": "-1.146",
    "rotationX": "0.0",
    "rotationY": "0.0",
    "rotationZ": "-0.0"
  },
  {
    "name": "LegLeftBack",
    "parent": "Body",
    "centerX": "1.048",
    "centerY": "1.2",
    "centerZ": "-1.0",
    "rotationX": "0.0",
    "rotationY": "0.0",
    "rotationZ": "-0.0"
  },
  {
    "name": "LegRightback",
    "parent": "Body",
    "centerX": "-1.048",
    "centerY": "1.2",
    "centerZ": "-1.0",
    "rotationX": "0.0",
    "rotationY": "0.0",
    "rotationZ": "-0.0"
  },
  {
    "name": "Head",
    "parent": "Body",
    "centerX": "-0.067",
    "centerY": "2.069",
    "centerZ": "2.38",
    "rotationX": "0.0",
    "rotationY": "0.0",
    "rotationZ": "-0.0"
  },
  {
    "name": "Legleftfront",
    "parent": "Body",
    "centerX": "1.0",
    "centerY": "1.2",
    "centerZ": "0.9",
    "rotationX": "0.0",
    "rotationY": "0.0",
    "rotationZ": "-0.0"
  },
  {
    "name": "Legrightfront",
    "parent": "Body",
    "centerX": "-1.0",
    "centerY": "1.2",
    "centerZ": "0.9",
    "rotationX": "0.0",
    "rotationY": "0.0",
    "rotationZ": "-0.0"
  }
]